gss_bi_udfs/__init__.py
gss_bi_udfs/io.py
gss_bi_udfs/merges.py
gss_bi_udfs/transforms.py
gss_bi_udfs/utils.py
gss_bi_udfs-0.1.1.dist-info/METADATA
gss_bi_udfs-0.1.1.dist-info/WHEEL
gss_bi_udfs-0.1.1.dist-info/top_level.txt
gss_bi_udfs-0.1.1.dist-info/RECORD
