Metadata-Version: 2.4
Name: gss-bi-udfs
Version: 0.1.1
Summary: Utilidades reutilizables para Spark y Delta Lake en arquitecturas Lakehouse.
Author: Geronimo Forconi
Requires-Python: >=3.8
Requires-Dist: pyspark>=3.0.0
